{"meta":{"id":"ustv-0443cb15-4abc-4f1a-9f6f-11ec690f281e","tvgId":"","name":"Lifetime","country":"USA","countryCode":"us","genre":"Entertainment","logo":"https://raw.githubusercontent.com/yowmamasita/usa-tv-next/main/public/logos/usa/lifetime-us.png","time":null,"type":"tv","poster":"https://raw.githubusercontent.com/yowmamasita/usa-tv-next/main/public/posters/usa/lifetime-us.png","genres":["Entertainment"],"streams":[{"url":"https://tvpass.org/live/LifetimeEast/sd","behaviorHints":{"notWebReady":true},"name":"SD","description":"TP"},{"url":"https://jmp2.uk/plu-63335b193583440007c859fb.m3u8","behaviorHints":{"notWebReady":true},"name":"HD","description":"HV:JMP2"},{"url":"https://tvpass.org/live/LifetimeMoviesEast/hd","behaviorHints":{"notWebReady":true},"name":"SD","description":"HV:TVPASS"}]}}